pydecoder/__init__.py
pydecoder/fields.py
pydecoder/json.py
pydecoder/operators.py
pydecoder/primitives.py
pydecoder/structs.py
pydecoder/xml.py
pydecoder-1.0.3.dist-info/DESCRIPTION.rst
pydecoder-1.0.3.dist-info/METADATA
pydecoder-1.0.3.dist-info/RECORD
pydecoder-1.0.3.dist-info/WHEEL
pydecoder-1.0.3.dist-info/metadata.json
pydecoder-1.0.3.dist-info/top_level.txt
