Metadata-Version: 2.0
Name: pydecoder
Version: 1.0.3
Summary: A XML, JSON,... decode library
Home-page: https://github.com/iodevs/pydecoder
Author: Jindrich Kralevic Smitka
Author-email: smitka.j@gmail.com
License: BSD license
Keywords: pydecoder
Platform: UNKNOWN
Classifier: Development Status :: 2 - Pre-Alpha
Classifier: Intended Audience :: Developers
Classifier: License :: OSI Approved :: BSD License
Classifier: Natural Language :: English
Classifier: Programming Language :: Python :: 2
Classifier: Programming Language :: Python :: 2.7
Classifier: Programming Language :: Python :: 3
Classifier: Programming Language :: Python :: 3.4
Classifier: Programming Language :: Python :: 3.5
Requires-Dist: pyresult (>=0.2.0)
Requires-Dist: six (>=1.7.3)
Requires-Dist: toolz (>=0.8.2)
